{"cameraMode":{"drawMode":0,"name":"Shaded","section":"Shading Mode"},"sceneLighting":true,"audioPlay":false,"sceneViewState":{"showFog":true,"showMaterialUpdate":false,"showSkybox":true,"showFlares":true,"showImageEffects":true,"showParticleSystems":true},"in2DMode":false,"pivot":{"x":9.847731590270996,"y":41.988800048828128,"z":54.42766571044922},"rotation":{"x":0.10986193269491196,"y":0.8720493912696838,"z":-0.22900742292404176,"w":0.41834887862205508},"size":21.09457778930664,"orthographic":false}